hexlab/__init__.py
hexlab/main.py
hexlab/color_math/__init__.py
hexlab/color_math/conversions.py
hexlab/color_math/distance.py
hexlab/color_math/luminance.py
hexlab/color_math/wcag_contrast.py
hexlab/constants/__init__.py
hexlab/constants/color_names.py
hexlab/constants/constants.py
hexlab/subcommands/__init__.py
hexlab/subcommands/adjust.py
hexlab/subcommands/convert.py
hexlab/subcommands/distinct.py
hexlab/subcommands/gradient.py
hexlab/subcommands/mix.py
hexlab/subcommands/registry.py
hexlab/subcommands/scheme.py
hexlab/subcommands/similar.py
hexlab/subcommands/vision.py
hexlab/utils/__init__.py
hexlab/utils/clamping.py
hexlab/utils/color_names_handler.py
hexlab/utils/formatting.py
hexlab/utils/hexlab_logger.py
hexlab/utils/input_handler.py
hexlab/utils/print_color_block.py
hexlab/utils/string_parser.py
hexlab/utils/truecolor.py
hexlab-0.0.5.dist-info/METADATA
hexlab-0.0.5.dist-info/WHEEL
hexlab-0.0.5.dist-info/entry_points.txt
hexlab-0.0.5.dist-info/top_level.txt
hexlab-0.0.5.dist-info/RECORD
