Metadata-Version: 2.4
Name: hexlab
Version: 0.0.5
Summary:  A feature-rich hex color exploration and manipulation tool.
Author-email: Mallik Mohammad Musaddiq <mallikmusaddiq1@gmail.com>
Classifier: Programming Language :: Python :: 3
Classifier: License :: OSI Approved :: MIT License
Classifier: Operating System :: OS Independent
Classifier: Topic :: Multimedia :: Graphics
Classifier: Environment :: Console
Requires-Python: >=3.7
